Workbook

Sheet Сводка
A1: Финмодели пилота «Парки и аллеи BI» · Т1–Т4
A2: Планировочные вилки к защите пилота · август 2026 · BI Service
A4: Как пользоваться. На листах моделей выберите объект из выпадающего списка (лист «Объекты», 32 территории, шорт-лист отмечен «Да») — обе площади подтянутся сами: озеленение из реестра, общая — фактический обмер Google Earth для группы A (для незамеренных: озеленение × коэффициент). Уборка и свет считаются от общей площади, озеленение и полив — от зелёной. Лист «Активы» — балансовая стоимость по справкам застройщиков; ремфонд = 1–1,5% в год от активов и планового CAPEX активации. Лист «Бюджет пилота» — годовое содержание пилота: Гранд Туран и Nexpo Юнион. Жёлтые ячейки — редактируемые ставки.
A9: Показатель | B9: Т1 · Flora 1+2 | C9: Т2 · Гранд Туран | D9: Т3 · Авеню 5 | E9: Т4 · Sphere Park
A10: Выбранный объект | B10: ='Т1 Транзитная'!B3 | C10: ='Т2 Активная'!B3 | D10: ='Т3 Сквер'!B3 | E10: ='Т4 Sphere Park'!B3
A11: Озеленение, м² | B11: ='Т1 Транзитная'!D3 | C11: ='Т2 Активная'!D3 | D11: ='Т3 Сквер'!D3 | E11: ='Т4 Sphere Park'!D3
A12: Общая площадь, м² | B12: ='Т1 Транзитная'!D4 | C12: ='Т2 Активная'!D4 | D12: ='Т3 Сквер'!D4 | E12: ='Т4 Sphere Park'!D4
A13: Активы на балансе, млн тг | B13: ='Т1 Транзитная'!B4 | C13: ='Т2 Активная'!B4 | D13: ='Т3 Сквер'!B4 | E13: ='Т4 Sphere Park'!B4
A14: Доходы, млн тг/год (мин) | B14: ='Т1 Транзитная'!C11 | C14: ='Т2 Активная'!C13 | D14: ='Т3 Сквер'!C13 | E14: ='Т4 Sphere Park'!C14
A15: Доходы, млн тг/год (макс) | B15: ='Т1 Транзитная'!D11 | C15: ='Т2 Активная'!D13 | D15: ='Т3 Сквер'!D13 | E15: ='Т4 Sphere Park'!D14
A16: OPEX, млн тг/год (мин) | B16: ='Т1 Транзитная'!C18 | C16: ='Т2 Активная'!C21 | D16: ='Т3 Сквер'!C22 | E16: ='Т4 Sphere Park'!C23
A17: OPEX, млн тг/год (макс) | B17: ='Т1 Транзитная'!D18 | C17: ='Т2 Активная'!D21 | D17: ='Т3 Сквер'!D22 | E17: ='Т4 Sphere Park'!D23
A18: Покрытие OPEX, консервативно | B18: =IFERROR('Т1 Транзитная'!C11/'Т1 Транзитная'!D18,0) | C18: =IFERROR('Т2 Активная'!C13/'Т2 Активная'!D21,0) | D18: =IFERROR('Т3 Сквер'!C13/'Т3 Сквер'!D22,0) | E18: =IFERROR('Т4 Sphere Park'!C14/'Т4 Sphere Park'!D23,0)
A19: Покрытие OPEX, по середине вилок | B19: =IFERROR(AVERAGE('Т1 Транзитная'!C11:D11)/AVERAGE('Т1 Транзитная'!C18:D18),0) | C19: =IFERROR(AVERAGE('Т2 Активная'!C13:D13)/AVERAGE('Т2 Активная'!C21:D21),0) | D19: =IFERROR(AVERAGE('Т3 Сквер'!C13:D13)/AVERAGE('Т3 Сквер'!C22:D22),0) | E19: =IFERROR(AVERAGE('Т4 Sphere Park'!C14:D14)/AVERAGE('Т4 Sphere Park'!C23:D23),0)
A20: Покрытие OPEX, оптимистично | B20: =IFERROR('Т1 Транзитная'!D11/'Т1 Транзитная'!C18,0) | C20: =IFERROR('Т2 Активная'!D13/'Т2 Активная'!C21,0) | D20: =IFERROR('Т3 Сквер'!D13/'Т3 Сквер'!C22,0) | E20: =IFERROR('Т4 Sphere Park'!D14/'Т4 Sphere Park'!C23,0)
A21: Целевой коридор пилота | B21: 10–30% | C21: 40–70% | D21: 70–100% | E21: 80–110%
A23: Вилки планировочные, для защиты подхода. Точные ставки дадут факт BI Green и нулевой спринт (сентябрь–октябрь 2026); полная модель с помесячной сезонностью собирается на них в ноябре 2026. CAPEX Sphere Park (~2,2 млрд тг, BTO) компенсируется бюджетом отдельно и в операционные модели не входит.

Sheet Объекты
A1: Справочник территорий · 31 объект реестра + Sphere Park
A2: Группы: A — обслуживает BI Green · B — переданы 29.07–03.08.2026 · C — не обслуживаются · D — переданы городу. Озеленение — из реестра; общая площадь группы A — обмер Google Earth (18.08.2026), Nexpo Юнион — оценка по аналогу (жёлтая ячейка, уточнить замером), прочие — озеленение × коэффициент. «Упр.» — Управление BI Service.
A3: № | B3: Территория | C3: Группа | D3: Тип | E3: Озеленение, м² | F3: Общая, м² | G3: Шорт-лист | H3: Статус / примечание | I3: Упр.
A4: 1 | B4: ул. Амман | C4: A | D4: Т2 | E4: 2500 | F4: =E4*Нормативы!$C$18 | G4: — | H4: не передан, обслуживает BI Green | I4: 1
A5: 2 | B5: Сквер Авеню 5 | C5: A | D5: Т3 | E5: 1700 | F5: 3114 | G5: Да | H5: не передан, обслуживает BI Green | I5: 1
A6: 3 | B6: Аллея Атлант вдоль Сарайшик | C6: A | D6: Т2 | E6: 1600 | F6: 4804 | G6: — | H6: не передан, обслуживает BI Green | I6: 1
A7: 4 | B7: Аллея Nexpo Классик | C7: A | D7: Т2 | E7: 6200 | F7: 10805 | G7: Да | H7: не передан, обслуживает BI Green | I7: 1
A8: 5 | B8: Аура Аллея | C8: A | D8: Т1 | E8: 800 | F8: 1415 | G8: Да | H8: не передан, обслуживает BI Green | I8: 2
A9: 6 | B9: Аллея Хедлайнер Эксклюзив | C9: A | D9: Т2 | E9: 4000 | F9: 4100 | G9: Да | H9: не передан, обслуживает BI Green | I9: 2
A10: 7 | B10: Аллея Гранд Туран Комфорт | C10: A | D10: Т2 | E10: 2300 | F10: 7059 | G10: Пилот | H10: не передан, обслуживает BI Green | I10: 4
A11: 8 | B11: Аллея ЖК Flora 1 | C11: A | D11: Т1 | E11: 338 | F11: 1512 | G11: Да | H11: не передан, обслуживает BI Green | I11: 2
A12: 9 | B12: Аллея ЖК Flora 2 | C12: A | D12: Т1 | E12: 338 | F12: 1210 | G12: Да | H12: не передан, обслуживает BI Green | I12: 2
A13: 10 | B13: Плейхаб Аква 1 | C13: A | D13: Т2 | E13: 2385 | F13: 2843 | G13: Да | H13: не передан, обслуживает BI Green; плейхаб, в шорт-листе как активная | I13: 2
A14: 11 | B14: Аллея Хедлайнер | C14: B | D14: Т2 | E14: 6800 | F14: =E14*Нормативы!$C$18 | G14: — | H14: передан 29.07.2026 | I14: —
A15: 12 | B15: Ремарк | C15: B | D15: Т2 | E15: 2930 | F15: =E15*Нормативы!$C$18 | G15: — | H15: передан 03.08.2026 | I15: —
A16: 13 | B16: Аллея Capital Park | C16: B | D16: Т2 | E16: 3650 | F16: =E16*Нормативы!$C$18 | G16: — | H16: передан 03.08.2026, придомовая | I16: —
A17: 14 | B17: Аллея Nura Esil 1, 2 | C17: B | D17: Т2 | E17: 1680 | F17: =E17*Нормативы!$C$18 | G17: — | H17: передан 03.08.2026, есть спортплощадка | I17: —
A18: 15 | B18: Аллея Nura Esil 4 | C18: B | D18: Т2 | E18: 1680 | F18: =E18*Нормативы!$C$18 | G18: — | H18: передан 03.08.2026 | I18: —
A19: 16 | B19: Аллея Камал | C19: B | D19: Т2 | E19: 3500 | F19: =E19*Нормативы!$C$18 | G19: — | H19: передан 03.08.2026 | I19: —
A20: 17 | B20: Аллея Арнау | C20: B | D20: Т2 | E20: 4000 | F20: =E20*Нормативы!$C$18 | G20: — | H20: передан 03.08.2026, аллея-парк | I20: —
A21: 18 | B21: Аллея Nexpo Юнион | C21: C | D21: Т2 | E21: 2419 | F21: 4200 | G21: Пилот | H21: не передан, не обслуживается | I21: —
A22: 19 | B22: Фридом — Зелёный Квартал | C22: C | D22: — | E22: 3600 | F22: =E22*Нормативы!$C$18 | G22: — | H22: парковка, вне типологии; уточнить юраудитом | I22: —
A23: 20 | B23: Де Люкс 4 | C23: C | D23: Т2 | E23: 4200 | F23: =E23*Нормативы!$C$18 | G23: — | H23: не передан, не обслуживается | I23: —
A24: 21 | B24: Насаждения ЖК Айтыс | C24: C | D24: Т1 | E24: 300 | F24: =E24*Нормативы!$C$18 | G24: — | H24: не передан, не обслуживается, придомовая | I24: —
A25: 22 | B25: Парк Авеню Эксклюзив | C25: C | D25: Т1 | E25: 680 | F25: =E25*Нормативы!$C$18 | G25: — | H25: не передан, не обслуживается | I25: —
A26: 23 | B26: Аллея Онли Мун | C26: C | D26: Т1 | E26: 600 | F26: =E26*Нормативы!$C$18 | G26: — | H26: не передан, не обслуживается | I26: —
A27: 24 | B27: Аллея Сердце Столицы 1, 2 | C27: C | D27: Т2 | E27: 1300 | F27: =E27*Нормативы!$C$18 | G27: — | H27: не передан, не обслуживается, придомовая | I27: —
A28: 25 | B28: Атлант Аллея | C28: D | D28: Т2 | E28: 1120 | F28: =E28*Нормативы!$C$18 | G28: — | H28: передан городу | I28: —
A29: 26 | B29: Аллея Премьера | C29: D | D29: Т2 | E29: 3900 | F29: =E29*Нормативы!$C$18 | G29: — | H29: передан городу | I29: —
A30: 27 | B30: Аллея Nexpo Сити | C30: D | D30: Т2 | E30: 2900 | F30: =E30*Нормативы!$C$18 | G30: — | H30: передан городу | I30: —
A31: 28 | B31: Парк и зелёная зона ЗК | C31: D | D31: Т3 | E31: 17000 | F31: =E31*Нормативы!$C$18 | G31: — | H31: передан городу, кандидат на ГЧП | I31: —
A32: 29 | B32: Плэй Хаб Сезым Кала | C32: D | D32: Т3 | E32: 3100 | F32: =E32*Нормативы!$C$18 | G32: — | H32: передан городу | I32: —
A33: 30 | B33: Аллея Поколение, Инфинити | C33: D | D33: Т2 | E33: 5500 | F33: =E33*Нормативы!$C$18 | G33: — | H33: передан городу | I33: —
A34: 31 | B34: Аллея Асыл Мура | C34: D | D34: Т2 | E34: 1100 | F34: =E34*Нормативы!$C$18 | G34: — | H34: передан городу | I34: —
A35: 32 | B35: Sphere Park | C35: ГЧП | D35: Т4 | E35: 70000 | F35: 90000 | G35: — | H35: проект ГЧП (BTO): парк 7 га + озеро 2 га у школы BINOM | I35: —
A36: 33 | B36: Аллеи ЖК Flora 1 + 2 (кластер) | C36: A | D36: Т1 | E36: 676 | F36: =F11+F12 | G36: — | H36: вспомогательная строка: две Flora вместе | I36: 2
A37: 34 | B37: Пилотный кластер: Хедлайнер + Flora + Аура | C37: A | D37: Т2 | E37: 5476 | F37: =F8+F9+F11+F12 | G37: — | H37: пилот: 4 аллеи одной командой — Хедлайнер Эксклюзив, Flora 1, Flora 2, Аура | I37: 2

Sheet Нормативы
A1: Справочник нормативов · расходная часть
A2: Жёлтые ячейки — редактируемые ставки. Меняете норматив здесь — расходная часть всех моделей пересчитывается. Заменить фактами BI Green.
A4: Показатель | B4: Ед. изм. | C4: Т1 мин | D4: Т1 макс | E4: Т2 мин | F4: Т2 макс | G4: Т3 мин | H4: Т3 макс | I4: Т4 мин | J4: Т4 макс
A5: Уборка и снегоуборка | B5: тг/м² общей пл. в месяц | C5: 60 | D5: 90 | E5: 30 | F5: 55 | G5: 60 | H5: 100 | I5: 30 | J5: 60
A6: Озеленение и полив (апр–окт) | B6: тг/м² озеленения в месяц | C6: 90 | D6: 160 | E6: 40 | F6: 70 | G6: 55 | H6: 90 | I6: 30 | J6: 60
A7: Свет, электро, digital | B7: тг/м² общей пл. в год | C7: 155 | D7: 250 | E7: 65 | F7: 115 | G7: 190 | H7: 315 | I7: 80 | J7: 150
A8: Доля ставки координатора | B8: доля ставки | C8: 0.2 | D8: 0.2 | E8: 0.33 | F8: 0.33 | G8: 0.6 | H8: 0.6 | I8: 0 | J8: 0
A9: Число событий в год | B9: шт | C9: 0 | D9: 0 | E9: 20 | F9: 30 | G9: 30 | H9: 45 | I9: 40 | J9: 60
A10: Зимний пакет (каток, горка, свет) | B10: млн тг/год | C10: 0 | D10: 0 | E10: 0 | F10: 0 | G10: 2.5 | H10: 4.5 | I10: 6 | J10: 12
A11: Персонал парка (только Т4) | B11: млн тг/год | C11: 0 | D11: 0 | E11: 0 | F11: 0 | G11: 0 | H11: 0 | I11: 8 | J11: 14
A12: CAPEX активации (разово, план) | B12: млн тг, единовременно | C12: 3 | D12: 8 | E12: 15 | F12: 40 | G12: 40 | H12: 120 | I12: 0 | J12: 0
A14: ОБЩИЕ НОРМАТИВЫ (мин / макс)
A15: Ставка координатора кластера | B15: тыс тг/мес | C15: 300 | D15: 420
A16: Цена события с продвижением | B16: тыс тг | C16: 95 | D16: 130
A17: Ремфонд, % в год от активов и вложений | B17: % в год | C17: 0.01 | D17: 0.015
A18: Коэффициент: общая площадь / озеленение | B18: × | C18: 2 | D18: 2

Sheet Активы
A1: Активы на балансе · справки застройщиков, август 2026
A2: Балансовая стоимость по справкам ТОО-застройщиков, млн тг. Ремфонд в моделях = ставка (лист «Нормативы») × (активы объекта + плановый CAPEX активации).
A3: Объект | B3: Озеленение, м² | C3: Общая, м² | D3: Покрытия | E3: Насаждения | F3: МАФы | G3: Свет | H3: Полив | I3: Земля | J3: Итого | K3: тыс тг/м² | L3: Что на балансе (по справке)
A4: Сквер Авеню 5 | B4: =IFERROR(INDEX(Объекты!$E$4:$E$37,MATCH($A4,Объекты!$B$4:$B$37,0)),"") | C4: =IFERROR(INDEX(Объекты!$F$4:$F$37,MATCH($A4,Объекты!$B$4:$B$37,0)),"") | D4: 0 | E4: 2.09 | F4: 0 | G4: 0 | H4: 0 | I4: 0 | J4: =SUM(D4:I4) | K4: =IFERROR(J4/C4*1000,"") | L4: только озеленение: 458 растений (вяз-изгородь 408 шт, 18 сосен, 11 елей). Света, МАФов и покрытий на балансе нет
A5: Аллея ЖК Flora 1 | B5: =IFERROR(INDEX(Объекты!$E$4:$E$37,MATCH($A5,Объекты!$B$4:$B$37,0)),"") | C5: =IFERROR(INDEX(Объекты!$F$4:$F$37,MATCH($A5,Объекты!$B$4:$B$37,0)),"") | D5: 2.5 | E5: 32.11 | F5: 2.23 | G5: 5.23 | H5: 0 | I5: 0 | J5: =SUM(D5:I5) | K5: =IFERROR(J5/C5*1000,"") | L5: брусчатка 279 м², 1 647 кустарников + 515 многолетников + 49 деревьев, 10 скамеек, 20 светильников, гирлянда 300 м
A6: Аллея ЖК Flora 2 | B6: =IFERROR(INDEX(Объекты!$E$4:$E$37,MATCH($A6,Объекты!$B$4:$B$37,0)),"") | C6: =IFERROR(INDEX(Объекты!$F$4:$F$37,MATCH($A6,Объекты!$B$4:$B$37,0)),"") | D6: 2.07 | E6: 20.68 | F6: 1.47 | G6: 5.85 | H6: 0 | I6: 0 | J6: =SUM(D6:I6) | K6: =IFERROR(J6/C6*1000,"") | L6: брусчатка 226 м², 1 087 кустарников + 34 дерева, 8 скамеек, 20 светильников, гирлянда 480 м
A7: Аллея Хедлайнер Эксклюзив | B7: =IFERROR(INDEX(Объекты!$E$4:$E$37,MATCH($A7,Объекты!$B$4:$B$37,0)),"") | C7: =IFERROR(INDEX(Объекты!$F$4:$F$37,MATCH($A7,Объекты!$B$4:$B$37,0)),"") | D7: 0 | E7: 0 | F7: 0 | G7: 0 | H7: 0 | I7: 0 | J7: =SUM(D7:I7) | K7: =IFERROR(J7/C7*1000,"") | L7: СПРАВКА ЗАПРОШЕНА у застройщика — внести после нулевого спринта (жёлтые ячейки)
A8: Аура Аллея | B8: =IFERROR(INDEX(Объекты!$E$4:$E$37,MATCH($A8,Объекты!$B$4:$B$37,0)),"") | C8: =IFERROR(INDEX(Объекты!$F$4:$F$37,MATCH($A8,Объекты!$B$4:$B$37,0)),"") | D8: 14.97 | E8: 38.65 | F8: 2.38 | G8: 4.26 | H8: 0 | I8: 0 | J8: =SUM(D8:I8) | K8: =IFERROR(J8/C8*1000,"") | L8: брусчатка 2 000 м², 2 226 кустарников + 42 дерева, 11 скамеек, 14 светильников 3,5 м, гирлянда 250 м
A9: Аллея Nexpo Классик | B9: =IFERROR(INDEX(Объекты!$E$4:$E$37,MATCH($A9,Объекты!$B$4:$B$37,0)),"") | C9: =IFERROR(INDEX(Объекты!$F$4:$F$37,MATCH($A9,Объекты!$B$4:$B$37,0)),"") | D9: 0 | E9: 21.89 | F9: 53.75 | G9: 1.3 | H9: 1.34 | I9: 57.09 | J9: =SUM(D9:I9) | K9: =IFERROR(J9/C9*1000,"") | L9: детское ядро: две горки (26,2 и 14,5 млн), карусель, батут, качели, тренажёр; автополив Hunter/Grundfos; земля 0,37 га
A10: Аллея Гранд Туран Комфорт | B10: =IFERROR(INDEX(Объекты!$E$4:$E$37,MATCH($A10,Объекты!$B$4:$B$37,0)),"") | C10: =IFERROR(INDEX(Объекты!$F$4:$F$37,MATCH($A10,Объекты!$B$4:$B$37,0)),"") | D10: 43.81 | E10: 46.89 | F10: 29.55 | G10: 8.81 | H10: 0 | I10: 0 | J10: =SUM(D10:I10) | K10: =IFERROR(J10/C10*1000,"") | L10: спецификация: покрытия ~5 200 м², 10 игровых комплексов, 27 скамеек, 21 урна, 23 опоры света (материалы, без НДС)
A11: Плейхаб Аква 1 | B11: =IFERROR(INDEX(Объекты!$E$4:$E$37,MATCH($A11,Объекты!$B$4:$B$37,0)),"") | C11: =IFERROR(INDEX(Объекты!$F$4:$F$37,MATCH($A11,Объекты!$B$4:$B$37,0)),"") | D11: 0 | E11: 6.83 | F11: 23 | G11: 1.26 | H11: 0.7 | I11: 0 | J11: =SUM(D11:I11) | K11: =IFERROR(J11/C11*1000,"") | L11: спортядро: огороженное поле 312 м² искусственной травы (борт 5 м), баскетбол, воркаут-серия, 4 вида качелей, канатный лаз
A12: Аллея Nexpo Юнион | B12: =IFERROR(INDEX(Объекты!$E$4:$E$37,MATCH($A12,Объекты!$B$4:$B$37,0)),"") | C12: =IFERROR(INDEX(Объекты!$F$4:$F$37,MATCH($A12,Объекты!$B$4:$B$37,0)),"") | D12: 0 | E12: 16.52 | F12: 52.11 | G12: 4.08 | H12: 0.72 | I12: 0 | J12: =SUM(D12:I12) | K12: =IFERROR(J12/C12*1000,"") | L12: игровой комплекс 42 млн (тартан, скалодром, тоннели), воркаут, теннисный стол, 54 светильника, автополив
A13: Фридом — Зелёный Квартал | B13: =IFERROR(INDEX(Объекты!$E$4:$E$37,MATCH($A13,Объекты!$B$4:$B$37,0)),"") | C13: =IFERROR(INDEX(Объекты!$F$4:$F$37,MATCH($A13,Объекты!$B$4:$B$37,0)),"") | D13: 0 | E13: 0 | F13: 0 | G13: 0 | H13: 0 | I13: 0 | J13: =SUM(D13:I13) | K13: =IFERROR(J13/C13*1000,"") | L13: справка без стоимостей: 47 деревьев (сосна, осина, клён) — вне шорт-листа
A15: Итого шорт-лист (9 объектов) | B15: =SUM(B4:B12) | C15: =SUM(C4:C12) | D15: =SUM(D4:D12) | E15: =SUM(E4:E12) | F15: =SUM(F4:F12) | G15: =SUM(G4:G12) | H15: =SUM(H4:H12) | I15: =SUM(I4:I12) | J15: =SUM(J4:J12) | K15: =IFERROR(J15/C15*1000,"")
A16: Аллеи ЖК Flora 1 + 2 (кластер) | B16: =IFERROR(INDEX(Объекты!$E$4:$E$37,MATCH($A16,Объекты!$B$4:$B$37,0)),"") | C16: =IFERROR(INDEX(Объекты!$F$4:$F$37,MATCH($A16,Объекты!$B$4:$B$37,0)),"") | D16: =D5+D6 | E16: =E5+E6 | F16: =F5+F6 | G16: =G5+G6 | H16: =H5+H6 | I16: =I5+I6 | J16: =SUM(D16:I16) | K16: =IFERROR(J16/C16*1000,"") | L16: строка для выпадающего списка Т1: сумма двух Flora
A17: Пилотный кластер: Хедлайнер + Flora + Аура | B17: =IFERROR(INDEX(Объекты!$E$4:$E$37,MATCH($A17,Объекты!$B$4:$B$37,0)),"") | C17: =IFERROR(INDEX(Объекты!$F$4:$F$37,MATCH($A17,Объекты!$B$4:$B$37,0)),"") | D17: =D7+D5+D6+D8 | E17: =E7+E5+E6+E8 | F17: =F7+F5+F6+F8 | G17: =G7+G5+G6+G8 | H17: =H7+H5+H6+H8 | I17: =I7+I5+I6+I8 | J17: =SUM(D17:I17) | K17: =IFERROR(J17/C17*1000,"") | L17: пилот: сумма четырёх аллей; активы Хедлайнера войдут после справки

Sheet Бюджет пилота
A1: Годовой бюджет содержания пилотного периметра
A2: Пилотный периметр: Гранд Туран и Nexpo Юнион. Уборка и свет от общей площади, озеленение от зелёной, ремфонд от активов на балансе, координация по долям ставок. Все ставки — лист «Нормативы». Программа активации — справочно, отдельной строкой.
A4: Объект | B4: Тип | C4: Озеленение, м² | D4: Общая, м² | E4: Уборка мин | F4: Уборка макс | G4: Озелен. мин | H4: Озелен. макс | I4: Свет мин | J4: Свет макс | K4: Ремфонд мин | L4: Ремфонд макс | M4: Итого мин | N4: Итого макс
A5: Аллея Гранд Туран Комфорт | B5: Т2 | C5: =IFERROR(INDEX(Объекты!$E$4:$E$37,MATCH($A5,Объекты!$B$4:$B$37,0)),"") | D5: =IFERROR(INDEX(Объекты!$F$4:$F$37,MATCH($A5,Объекты!$B$4:$B$37,0)),"") | E5: =$D5*Нормативы!E5*12/1000000 | F5: =$D5*Нормативы!F5*12/1000000 | G5: =$C5*Нормативы!E6*7/1000000 | H5: =$C5*Нормативы!F6*7/1000000 | I5: =$D5*Нормативы!E7/1000000 | J5: =$D5*Нормативы!F7/1000000 | K5: =Нормативы!$C$17*IFERROR(INDEX(Активы!$J$4:$J$17,MATCH($A5,Активы!$A$4:$A$17,0)),0) | L5: =Нормативы!$D$17*IFERROR(INDEX(Активы!$J$4:$J$17,MATCH($A5,Активы!$A$4:$A$17,0)),0) | M5: =E5+G5+I5+K5 | N5: =F5+H5+J5+L5
A6: Аллея Nexpo Юнион | B6: Т2 | C6: =IFERROR(INDEX(Объекты!$E$4:$E$37,MATCH($A6,Объекты!$B$4:$B$37,0)),"") | D6: =IFERROR(INDEX(Объекты!$F$4:$F$37,MATCH($A6,Объекты!$B$4:$B$37,0)),"") | E6: =$D6*Нормативы!E5*12/1000000 | F6: =$D6*Нормативы!F5*12/1000000 | G6: =$C6*Нормативы!E6*7/1000000 | H6: =$C6*Нормативы!F6*7/1000000 | I6: =$D6*Нормативы!E7/1000000 | J6: =$D6*Нормативы!F7/1000000 | K6: =Нормативы!$C$17*IFERROR(INDEX(Активы!$J$4:$J$17,MATCH($A6,Активы!$A$4:$A$17,0)),0) | L6: =Нормативы!$D$17*IFERROR(INDEX(Активы!$J$4:$J$17,MATCH($A6,Активы!$A$4:$A$17,0)),0) | M6: =E6+G6+I6+K6 | N6: =F6+H6+J6+L6
A7: Координатор Гранд Турана (доля Т2) | B7: 0,33 ставки на объект | M7: =Нормативы!E8*Нормативы!$C$15*12/1000 | N7: =Нормативы!F8*Нормативы!$D$15*12/1000
A8: Координатор Nexpo Юниона (доля Т2) | B8: 0,33 ставки; при общем координаторе на два контура ставка складывается | M8: =Нормативы!E8*Нормативы!$C$15*12/1000 | N8: =Нормативы!F8*Нормативы!$D$15*12/1000
A10: Гранд Туран, итого | M10: =M5+M7 | N10: =N5+N7
A11: Nexpo Юнион, итого | M11: =M6+M8 | N11: =N6+N8
A12: ПИЛОТ: СОДЕРЖАНИЕ, ИТОГО | M12: =M10+M11 | N12: =N10+N11
A14: Программа активации (справочно, два контура) | B14: события по нормативу Т2 на каждый контур; это активация, в содержание не входит | M14: =2*Нормативы!E9*Нормативы!$C$16/1000 | N14: =2*Нормативы!F9*Нормативы!$D$16/1000
A16: Nexpo Юнион не передан и сейчас не обслуживается: его содержание — новые деньги, а не перераспределение. Общая площадь оценочная, замер уточнит уборку и свет. Вилки планировочные, для защиты подхода. Точные ставки дадут факт BI Green и нулевой спринт (сентябрь–октябрь 2026); полная модель с помесячной сезонностью собирается на них в ноябре 2026.

Sheet Т1 Транзитная
A1: Финмодель Т1 · Транзитная аллея
A3: Объект (выберите из списка): | B3: Аллеи ЖК Flora 1 + 2 (кластер) | C3: Озеленение, м²: | D3: =IFERROR(INDEX(Объекты!$E$4:$E$37,MATCH($B$3,Объекты!$B$4:$B$37,0)),0)
A4: Активы на балансе, млн тг: | B4: =IFERROR(INDEX(Активы!$J$4:$J$17,MATCH($B$3,Активы!$A$4:$A$17,0)),0) | C4: Общая площадь, м²: | D4: =IFERROR(INDEX(Объекты!$F$4:$F$37,MATCH($B$3,Объекты!$B$4:$B$37,0)),0)
A6: Статья | B6: Как считаем / привязка | C6: Мин, млн тг/год | D6: Макс, млн тг/год
A7: ДОХОДЫ (вилки: зависят от программы, не от площади)
A8: Вендинг, 1 автомат | B8: аренда точки 25–45 тыс тг/мес | C8: 0.3 | D8: 0.5
A9: Спонсорство «Усынови клумбу» | B9: 3–5 спонсоров по 80–150 тыс тг/год | C9: 0.2 | D9: 0.6
A10: Реклама на навигации | B10: при подходящем юрстатусе земли | C10: 0 | D10: 0.4
A11: Доходы, итого | C11: =SUM(C8:C10) | D11: =SUM(D8:D10)
A12: РАСХОДЫ (OPEX): формулы «площадь × нормативы»
A13: Уборка и снегоуборка | B13: общая площадь × норматив × 12 мес | C13: =$D$4*Нормативы!C5*12/1000000 | D13: =$D$4*Нормативы!D5*12/1000000
A14: Озеленение и полив | B14: озеленение × норматив × 7 мес (апр–окт) | C14: =$D$3*Нормативы!C6*7/1000000 | D14: =$D$3*Нормативы!D6*7/1000000
A15: Свет, электро, digital | B15: общая площадь × годовой норматив | C15: =$D$4*Нормативы!C7/1000000 | D15: =$D$4*Нормативы!D7/1000000
A16: Координатор кластера | B16: ставка × доля × 12 мес | C16: =Нормативы!$C$15*Нормативы!C8*12/1000 | D16: =Нормативы!$D$15*Нормативы!D8*12/1000
A17: Ремфонд | B17: % в год от активов на балансе + CAPEX активации | C17: =Нормативы!$C$17*($B$4+Нормативы!C12) | D17: =Нормативы!$D$17*($B$4+Нормативы!D12)
A18: OPEX, итого | C18: =SUM(C13:C17) | D18: =SUM(D13:D17)
A20: ПОКРЫТИЕ OPEX ДОХОДАМИ
A21: Консервативный сценарий | B21: низ доходов / верх расходов | C21: =IFERROR(C11/D18,0)
A22: По середине вилок | B22: средние значения обеих вилок | C22: =IFERROR(AVERAGE(C11:D11)/AVERAGE(C18:D18),0)
A23: Оптимистичный сценарий | B23: верх доходов / низ расходов | C23: =IFERROR(D11/C18,0)
A24: Целевой коридор пилота | C24: 10–30%
A26: ЧТО ДОЛЖНО СОЙТИСЬ
A27: • Кластер: общий координатор и бригада, не своя
A28: • Спонсоры продлеваются на второй год
A29: • Юрстатус пропускает рекламу на стелах
A31: Вилки планировочные, для защиты подхода. Точные ставки дадут факт BI Green и нулевой спринт (сентябрь–октябрь 2026); полная модель с помесячной сезонностью собирается на них в ноябре 2026.

Sheet Т2 Активная
A1: Финмодель Т2 · Активная аллея
A3: Объект (выберите из списка): | B3: Аллея Гранд Туран Комфорт | C3: Озеленение, м²: | D3: =IFERROR(INDEX(Объекты!$E$4:$E$37,MATCH($B$3,Объекты!$B$4:$B$37,0)),0)
A4: Активы на балансе, млн тг: | B4: =IFERROR(INDEX(Активы!$J$4:$J$17,MATCH($B$3,Активы!$A$4:$A$17,0)),0) | C4: Общая площадь, м²: | D4: =IFERROR(INDEX(Объекты!$F$4:$F$37,MATCH($B$3,Объекты!$B$4:$B$37,0)),0)
A6: Статья | B6: Как считаем / привязка | C6: Мин, млн тг/год | D6: Макс, млн тг/год
A7: ДОХОДЫ (вилки: зависят от программы, не от площади)
A8: НТО-якорь: кофе-павильон | B8: аренда 120–250 тыс тг/мес + 2–5% оборота | C8: 1.8 | D8: 3.6
A9: Ярмарка выходного дня | B9: 12–16 ярмарок, 15–25 мест по 3–5 тыс тг | C9: 0.7 | D9: 1.8
A10: Секции и кикшеринг | B10: слоты тренерам + rev-share операторов | C10: 0.6 | D10: 1.6
A11: Digital-экран и реклама | B11: при подходящем юрстатусе земли | C11: 0.8 | D11: 2
A12: Спонсорство объектов | B12: воркаут, клумбы, скамейки | C12: 0.5 | D12: 1.2
A13: Доходы, итого | C13: =SUM(C8:C12) | D13: =SUM(D8:D12)
A14: РАСХОДЫ (OPEX): формулы «площадь × нормативы»
A15: Уборка и снегоуборка | B15: общая площадь × норматив × 12 мес | C15: =$D$4*Нормативы!E5*12/1000000 | D15: =$D$4*Нормативы!F5*12/1000000
A16: Озеленение и полив | B16: озеленение × норматив × 7 мес (апр–окт) | C16: =$D$3*Нормативы!E6*7/1000000 | D16: =$D$3*Нормативы!F6*7/1000000
A17: Свет, электро, digital | B17: общая площадь × годовой норматив | C17: =$D$4*Нормативы!E7/1000000 | D17: =$D$4*Нормативы!F7/1000000
A18: Программа и маркетинг | B18: число событий × цена события | C18: =Нормативы!E9*Нормативы!$C$16/1000 | D18: =Нормативы!F9*Нормативы!$D$16/1000
A19: Координатор кластера | B19: ставка × доля × 12 мес | C19: =Нормативы!$C$15*Нормативы!E8*12/1000 | D19: =Нормативы!$D$15*Нормативы!F8*12/1000
A20: Ремфонд | B20: % в год от активов на балансе + CAPEX активации | C20: =Нормативы!$C$17*($B$4+Нормативы!E12) | D20: =Нормативы!$D$17*($B$4+Нормативы!F12)
A21: OPEX, итого | C21: =SUM(C15:C20) | D21: =SUM(D15:D20)
A23: ПОКРЫТИЕ OPEX ДОХОДАМИ
A24: Консервативный сценарий | B24: низ доходов / верх расходов | C24: =IFERROR(C13/D21,0)
A25: По середине вилок | B25: средние значения обеих вилок | C25: =IFERROR(AVERAGE(C13:D13)/AVERAGE(C21:D21),0)
A26: Оптимистичный сценарий | B26: верх доходов / низ расходов | C26: =IFERROR(D13/C21,0)
A27: Целевой коридор пилота | C27: 40–70%
A29: ЧТО ДОЛЖНО СОЙТИСЬ
A30: • Справка по активам Хедлайнера получена, суммы внесены в лист «Активы»
A31: • Якорь-павильон заполнен с мая по сентябрь
A32: • Ярмарка стала привычкой района: 12+ за сезон
A33: • Вечерние слоты секций выкуплены
A35: Вилки планировочные, для защиты подхода. Точные ставки дадут факт BI Green и нулевой спринт (сентябрь–октябрь 2026); полная модель с помесячной сезонностью собирается на них в ноябре 2026.

Sheet Т3 Сквер
A1: Финмодель Т3 · Сквер / плейхаб
A3: Объект (выберите из списка): | B3: Сквер Авеню 5 | C3: Озеленение, м²: | D3: =IFERROR(INDEX(Объекты!$E$4:$E$37,MATCH($B$3,Объекты!$B$4:$B$37,0)),0)
A4: Активы на балансе, млн тг: | B4: =IFERROR(INDEX(Активы!$J$4:$J$17,MATCH($B$3,Активы!$A$4:$A$17,0)),0) | C4: Общая площадь, м²: | D4: =IFERROR(INDEX(Объекты!$F$4:$F$37,MATCH($B$3,Объекты!$B$4:$B$37,0)),0)
A6: Статья | B6: Как считаем / привязка | C6: Мин, млн тг/год | D6: Макс, млн тг/год
A7: ДОХОДЫ (вилки: зависят от программы, не от площади)
A8: Две НТО-точки | B8: кофе и выпечка: аренда + % оборота | C8: 2.4 | D8: 4.8
A9: Каток: прокат и билеты | B9: компактный контур, 120–160 дней | C9: 1.5 | D9: 3.5
A10: Событийная аренда | B10: 10–18 частных и корпоративных событий | C10: 1 | D10: 2.8
A11: Ярмарки, маркеты, секции | B11: круглогодичный календарь | C11: 1.3 | D11: 2.6
A12: Спонсор года и реклама | B12: один якорный партнёр + экран | C12: 1.5 | D12: 3.7
A13: Доходы, итого | C13: =SUM(C8:C12) | D13: =SUM(D8:D12)
A14: РАСХОДЫ (OPEX): формулы «площадь × нормативы»
A15: Уборка и снегоуборка | B15: общая площадь × норматив × 12 мес | C15: =$D$4*Нормативы!G5*12/1000000 | D15: =$D$4*Нормативы!H5*12/1000000
A16: Озеленение и полив | B16: озеленение × норматив × 7 мес (апр–окт) | C16: =$D$3*Нормативы!G6*7/1000000 | D16: =$D$3*Нормативы!H6*7/1000000
A17: Свет, электро, digital | B17: общая площадь × годовой норматив | C17: =$D$4*Нормативы!G7/1000000 | D17: =$D$4*Нормативы!H7/1000000
A18: Зимний пакет | B18: норматив, млн тг/год | C18: =Нормативы!G10 | D18: =Нормативы!H10
A19: Программа и маркетинг | B19: число событий × цена события | C19: =Нормативы!G9*Нормативы!$C$16/1000 | D19: =Нормативы!H9*Нормативы!$D$16/1000
A20: Координатор кластера | B20: ставка × доля × 12 мес | C20: =Нормативы!$C$15*Нормативы!G8*12/1000 | D20: =Нормативы!$D$15*Нормативы!H8*12/1000
A21: Ремфонд | B21: % в год от активов на балансе + CAPEX активации | C21: =Нормативы!$C$17*($B$4+Нормативы!G12) | D21: =Нормативы!$D$17*($B$4+Нормативы!H12)
A22: OPEX, итого | C22: =SUM(C15:C21) | D22: =SUM(D15:D21)
A24: ПОКРЫТИЕ OPEX ДОХОДАМИ
A25: Консервативный сценарий | B25: низ доходов / верх расходов | C25: =IFERROR(C13/D22,0)
A26: По середине вилок | B26: средние значения обеих вилок | C26: =IFERROR(AVERAGE(C13:D13)/AVERAGE(C22:D22),0)
A27: Оптимистичный сценарий | B27: верх доходов / низ расходов | C27: =IFERROR(D13/C22,0)
A28: Целевой коридор пилота | C28: 70–100%
A30: ЧТО ДОЛЖНО СОЙТИСЬ
A31: • Каток отработал первую зиму без простоев
A32: • Заявок на события больше, чем слотов
A33: • Спонсор года подписан до старта сезона
A35: Вилки планировочные, для защиты подхода. Точные ставки дадут факт BI Green и нулевой спринт (сентябрь–октябрь 2026); полная модель с помесячной сезонностью собирается на них в ноябре 2026.

Sheet Т4 Sphere Park
A1: Финмодель Т4 · Парк по ГЧП (BTO)
A3: Объект (выберите из списка): | B3: Sphere Park | C3: Озеленение, м²: | D3: =IFERROR(INDEX(Объекты!$E$4:$E$37,MATCH($B$3,Объекты!$B$4:$B$37,0)),0)
A4: Активы на балансе, млн тг: | B4: =IFERROR(INDEX(Активы!$J$4:$J$17,MATCH($B$3,Активы!$A$4:$A$17,0)),0) | C4: Общая площадь, м²: | D4: =IFERROR(INDEX(Объекты!$F$4:$F$37,MATCH($B$3,Объекты!$B$4:$B$37,0)),0)
A6: Статья | B6: Как считаем / привязка | C6: Мин, млн тг/год | D6: Макс, млн тг/год
A7: ДОХОДЫ (вилки: зависят от программы, не от площади)
A8: Компенсация эксплуатации (акимат) | B8: структура BTO: ~0,33 млрд тг за 5 лет | C8: 55 | D8: 70
A9: НТО-точки, 3–5 шт | B9: кофе, стритфуд, прокат | C9: 3 | D9: 6
A10: Каток и зимний прокат | B10: большой контур, 120–160 дней | C10: 8 | D10: 16
A11: Событийная аренда и фестивали | B11: городской масштаб | C11: 3 | D11: 8
A12: Ярмарки и маркеты | B12: круглогодично | C12: 2 | D12: 4
A13: Спонсоры и реклама | B13: якорные партнёры | C13: 2 | D13: 5
A14: Доходы, итого | C14: =SUM(C8:C13) | D14: =SUM(D8:D13)
A15: РАСХОДЫ (OPEX): формулы «площадь × нормативы»
A16: Уборка и снегоуборка | B16: общая площадь × норматив × 12 мес | C16: =$D$4*Нормативы!I5*12/1000000 | D16: =$D$4*Нормативы!J5*12/1000000
A17: Озеленение и полив | B17: озеленение × норматив × 7 мес (апр–окт) | C17: =$D$3*Нормативы!I6*7/1000000 | D17: =$D$3*Нормативы!J6*7/1000000
A18: Свет, электро, digital | B18: общая площадь × годовой норматив | C18: =$D$4*Нормативы!I7/1000000 | D18: =$D$4*Нормативы!J7/1000000
A19: Зимний пакет | B19: норматив, млн тг/год | C19: =Нормативы!I10 | D19: =Нормативы!J10
A20: Программа и маркетинг | B20: число событий × цена события | C20: =Нормативы!I9*Нормативы!$C$16/1000 | D20: =Нормативы!J9*Нормативы!$D$16/1000
A21: Персонал парка | B21: норматив, млн тг/год | C21: =Нормативы!I11 | D21: =Нормативы!J11
A22: Ремфонд | B22: % в год от активов на балансе + CAPEX активации | C22: =Нормативы!$C$17*($B$4+Нормативы!I12) | D22: =Нормативы!$D$17*($B$4+Нормативы!J12)
A23: OPEX, итого | C23: =SUM(C16:C22) | D23: =SUM(D16:D22)
A25: ПОКРЫТИЕ OPEX ДОХОДАМИ
A26: Консервативный сценарий | B26: низ доходов / верх расходов | C26: =IFERROR(C14/D23,0)
A27: По середине вилок | B27: средние значения обеих вилок | C27: =IFERROR(AVERAGE(C14:D14)/AVERAGE(C23:D23),0)
A28: Оптимистичный сценарий | B28: верх доходов / низ расходов | C28: =IFERROR(D14/C23,0)
A29: Целевой коридор пилота | C29: 80–110%
A31: ЧТО ДОЛЖНО СОЙТИСЬ
A32: • Ремфонд и капремонт сидят в компенсации эксплуатации (BTO), в OPEX не дублируются
A33: • ГЧП-договор подписан, компенсация в бюджете МИО
A34: • Каток и события дотягивают покрытие до 100%+
A35: • Стандарт содержания выше городского бенчмарка
A36: • CAPEX ~2,2 млрд тг компенсируется бюджетом МИО отдельно (2026–2031) — в операционную модель не входит
A38: Вилки планировочные, для защиты подхода. Точные ставки дадут факт BI Green и нулевой спринт (сентябрь–октябрь 2026); полная модель с помесячной сезонностью собирается на них в ноябре 2026.
