Workbook

Sheet Сводка
A1: Финмодели пилота «Парки и аллеи BI» · Т1 / Т2 / Т3
A2: Планировочные вилки к защите пилота · август 2026 · BI Service
A4: Как пользоваться: жёлтые ячейки на листах моделей — редактируемые ставки-вилки (синий шрифт). Меняйте их, итоги и покрытие OPEX пересчитаются сами. Остальные ячейки — формулы, их не трогаем.
A7: Показатель | B7: Т1 · Аура | C7: Т2 · Nexpo Классик | D7: Т3 · Аква
A8: Тип территории | B8: Транзитная аллея | C8: Активная аллея | D8: Плейхаб
A9: Площадь, м² | B9: 800 | C9: 6200 | D9: 2385
A10: Доходы, млн тг/год (мин) | B10: ='Т1 Аура'!C9 | C10: ='Т2 Nexpo Классик'!C11 | D10: ='Т3 Аква'!C11
A11: Доходы, млн тг/год (макс) | B11: ='Т1 Аура'!D9 | C11: ='Т2 Nexpo Классик'!D11 | D11: ='Т3 Аква'!D11
A12: OPEX, млн тг/год (мин) | B12: ='Т1 Аура'!C16 | C12: ='Т2 Nexpo Классик'!C19 | D12: ='Т3 Аква'!C20
A13: OPEX, млн тг/год (макс) | B13: ='Т1 Аура'!D16 | C13: ='Т2 Nexpo Классик'!D19 | D13: ='Т3 Аква'!D20
A14: Покрытие OPEX, консервативно | B14: =IFERROR('Т1 Аура'!C9/'Т1 Аура'!D16,0) | C14: =IFERROR('Т2 Nexpo Классик'!C11/'Т2 Nexpo Классик'!D19,0) | D14: =IFERROR('Т3 Аква'!C11/'Т3 Аква'!D20,0)
A15: Покрытие OPEX, по середине вилок | B15: =IFERROR(AVERAGE('Т1 Аура'!C9:D9)/AVERAGE('Т1 Аура'!C16:D16),0) | C15: =IFERROR(AVERAGE('Т2 Nexpo Классик'!C11:D11)/AVERAGE('Т2 Nexpo Классик'!C19:D19),0) | D15: =IFERROR(AVERAGE('Т3 Аква'!C11:D11)/AVERAGE('Т3 Аква'!C20:D20),0)
A16: Покрытие OPEX, оптимистично | B16: =IFERROR('Т1 Аура'!D9/'Т1 Аура'!C16,0) | C16: =IFERROR('Т2 Nexpo Классик'!D11/'Т2 Nexpo Классик'!C19,0) | D16: =IFERROR('Т3 Аква'!D11/'Т3 Аква'!C20,0)
A17: Целевой коридор пилота | B17: 10–30% | C17: 40–70% | D17: 70–100%
A19: Вилки планировочные, для защиты подхода. Точные ставки дадут факт BI Green и нулевой спринт (сентябрь–октябрь 2026); полная Excel-модель с помесячной сезонностью собирается на них в ноябре 2026. Источники подхода: docs/research/park-pilot-concept.md.

Sheet Т1 Аура
A1: Финмодель Т1 · Транзитная аллея
A2: Аура Аллея, 800 м² · пилотный объект группы A
A4: Статья | B4: Как считаем | C4: Мин, млн тг/год | D4: Макс, млн тг/год
A5: ДОХОДЫ
A6: Вендинг, 1 автомат | B6: аренда точки 25–45 тыс тг/мес | C6: 0.3 | D6: 0.5
A7: Спонсорство «Усынови клумбу» | B7: 3–5 спонсоров по 80–150 тыс тг/год | C7: 0.2 | D7: 0.6
A8: Реклама на навигации | B8: при подходящем юрстатусе земли | C8: 0 | D8: 0.4
A9: Доходы, итого | C9: =SUM(C6:C8) | D9: =SUM(D6:D8)
A10: РАСХОДЫ (OPEX)
A11: Уборка и снегоуборка | B11: 800 м² по 120–175 тг/м² в месяц | C11: 1.15 | D11: 1.7
A12: Озеленение и полив | B12: апрель–октябрь | C12: 0.5 | D12: 0.9
A13: Освещение | B13: тариф и длинная зимняя ночь | C13: 0.25 | D13: 0.4
A14: Координатор кластера | B14: 1/5 ставки на объект | C14: 0.75 | D14: 1
A15: Ремфонд и мелкий ремонт | B15: 5–7% от OPEX | C15: 0.35 | D15: 0.5
A16: OPEX, итого | C16: =SUM(C11:C15) | D16: =SUM(D11:D15)
A18: ПОКРЫТИЕ OPEX ДОХОДАМИ
A19: Консервативный сценарий | B19: низ доходов / верх расходов | C19: =IFERROR(C9/D16,0)
A20: По середине вилок | B20: средние значения обеих вилок | C20: =IFERROR(AVERAGE(C9:D9)/AVERAGE(C16:D16),0)
A21: Оптимистичный сценарий | B21: верх доходов / низ расходов | C21: =IFERROR(D9/C16,0)
A22: Целевой коридор пилота | C22: 10–30%
A24: ЧТО ДОЛЖНО СОЙТИСЬ
A25: • Кластер: общий координатор и бригада, не своя
A26: • Спонсоры продлеваются на второй год
A27: • Юрстатус пропускает рекламу на стелах
A29: Вилки планировочные, для защиты подхода. Точные ставки дадут факт BI Green и нулевой спринт (сентябрь–октябрь 2026); полная Excel-модель с помесячной сезонностью собирается на них в ноябре 2026.

Sheet Т2 Nexpo Классик
A1: Финмодель Т2 · Активная аллея
A2: Аллея Nexpo Классик, 6 200 м² · пилотный объект группы A
A4: Статья | B4: Как считаем | C4: Мин, млн тг/год | D4: Макс, млн тг/год
A5: ДОХОДЫ
A6: НТО-якорь: кофе-павильон | B6: аренда 120–250 тыс тг/мес + 2–5% оборота | C6: 1.8 | D6: 3.6
A7: Ярмарка выходного дня | B7: 12–16 ярмарок, 15–25 мест по 3–5 тыс тг | C7: 0.7 | D7: 1.8
A8: Секции и кикшеринг | B8: слоты тренерам + rev-share операторов | C8: 0.6 | D8: 1.6
A9: Digital-экран и реклама | B9: при подходящем юрстатусе земли | C9: 0.8 | D9: 2
A10: Спонсорство объектов | B10: воркаут, клумбы, скамейки | C10: 0.5 | D10: 1.2
A11: Доходы, итого | C11: =SUM(C6:C10) | D11: =SUM(D6:D10)
A12: РАСХОДЫ (OPEX)
A13: Уборка и снегоуборка | B13: 6 200 м² по 60–110 тг/м² в месяц | C13: 4.5 | D13: 8.2
A14: Озеленение и полив | B14: апрель–октябрь | C14: 1.8 | D14: 3
A15: Свет и электро для НТО | B15: включая событийные подключения | C15: 0.8 | D15: 1.4
A16: Программа и маркетинг | B16: 20–30 событий по 60–120 тыс тг | C16: 1.9 | D16: 3.9
A17: Координатор кластера | B17: 1/3 ставки на объект | C17: 1.2 | D17: 1.6
A18: Ремфонд | B18: 5–7% от OPEX | C18: 0.7 | D18: 1.2
A19: OPEX, итого | C19: =SUM(C13:C18) | D19: =SUM(D13:D18)
A21: ПОКРЫТИЕ OPEX ДОХОДАМИ
A22: Консервативный сценарий | B22: низ доходов / верх расходов | C22: =IFERROR(C11/D19,0)
A23: По середине вилок | B23: средние значения обеих вилок | C23: =IFERROR(AVERAGE(C11:D11)/AVERAGE(C19:D19),0)
A24: Оптимистичный сценарий | B24: верх доходов / низ расходов | C24: =IFERROR(D11/C19,0)
A25: Целевой коридор пилота | C25: 40–70%
A27: ЧТО ДОЛЖНО СОЙТИСЬ
A28: • Якорь-павильон заполнен с мая по сентябрь
A29: • Ярмарка стала привычкой района: 12+ за сезон
A30: • Вечерние слоты секций выкуплены
A32: Вилки планировочные, для защиты подхода. Точные ставки дадут факт BI Green и нулевой спринт (сентябрь–октябрь 2026); полная Excel-модель с помесячной сезонностью собирается на них в ноябре 2026.

Sheet Т3 Аква
A1: Финмодель Т3 · Плейхаб
A2: Плейхаб Аква 1, 2 385 м² · пилотный объект группы A, флагман
A4: Статья | B4: Как считаем | C4: Мин, млн тг/год | D4: Макс, млн тг/год
A5: ДОХОДЫ
A6: Две НТО-точки | B6: кофе и выпечка: аренда + % оборота | C6: 2.4 | D6: 4.8
A7: Каток: прокат и билеты | B7: 120–160 дней зимнего сезона | C7: 2.5 | D7: 5.5
A8: Событийная аренда | B8: 10–18 частных и корпоративных событий | C8: 1 | D8: 2.8
A9: Ярмарки, маркеты, секции | B9: круглогодичный календарь | C9: 1.3 | D9: 2.6
A10: Спонсор года и реклама | B10: один якорный партнёр + экран | C10: 1.5 | D10: 3.7
A11: Доходы, итого | C11: =SUM(C6:C10) | D11: =SUM(D6:D10)
A12: РАСХОДЫ (OPEX)
A13: Уборка и снегоуборка | B13: 2 385 м² по 120–200 тг/м² в месяц, интенсив | C13: 3.4 | D13: 5.7
A14: Озеленение и полив | B14: апрель–октябрь | C14: 0.9 | D14: 1.5
A15: Свет, электро, Wi-Fi | B15: включая архитектурную подсветку | C15: 0.9 | D15: 1.5
A16: Зимний пакет | B16: заливка, уход за льдом, персонал проката | C16: 2.5 | D16: 4.5
A17: Программа и маркетинг | B17: 30–45 событий в год | C17: 3.1 | D17: 5.5
A18: Координатор и событийный менеджер | B18: доли двух ставок | C18: 2 | D18: 3
A19: Ремфонд | B19: 5–7% от OPEX | C19: 0.8 | D19: 1.4
A20: OPEX, итого | C20: =SUM(C13:C19) | D20: =SUM(D13:D19)
A22: ПОКРЫТИЕ OPEX ДОХОДАМИ
A23: Консервативный сценарий | B23: низ доходов / верх расходов | C23: =IFERROR(C11/D20,0)
A24: По середине вилок | B24: средние значения обеих вилок | C24: =IFERROR(AVERAGE(C11:D11)/AVERAGE(C20:D20),0)
A25: Оптимистичный сценарий | B25: верх доходов / низ расходов | C25: =IFERROR(D11/C20,0)
A26: Целевой коридор пилота | C26: 70–100%
A28: ЧТО ДОЛЖНО СОЙТИСЬ
A29: • Каток отработал первую зиму без простоев
A30: • Заявок на события больше, чем слотов
A31: • Спонсор года подписан до старта сезона
A33: Вилки планировочные, для защиты подхода. Точные ставки дадут факт BI Green и нулевой спринт (сентябрь–октябрь 2026); полная Excel-модель с помесячной сезонностью собирается на них в ноябре 2026.
